README.txt
setup.py
package_1/__init__.py
package_1/at_content.py
upload_dnatools_36.egg-info/PKG-INFO
upload_dnatools_36.egg-info/SOURCES.txt
upload_dnatools_36.egg-info/dependency_links.txt
upload_dnatools_36.egg-info/top_level.txt